gcb202a22/__init__.py
gcb202a22/data.pkl
gcb202a22-0.4.dist-info/METADATA
gcb202a22-0.4.dist-info/WHEEL
gcb202a22-0.4.dist-info/top_level.txt
gcb202a22-0.4.dist-info/RECORD
